yaman/__init__.py
yaman/interface/__init__.py
yaman/interface/guake.py
yaman/interface/yakuake.py
yaman/sessionBuilder.py
yaman/sessionManager.py
yaman/yaman.py
yaman-0.1.2.dist-info/LICENSE
yaman-0.1.2.dist-info/METADATA
yaman-0.1.2.dist-info/WHEEL
yaman-0.1.2.dist-info/entry_points.txt
yaman-0.1.2.dist-info/RECORD
